{
	"id": "e4c931ac-9e37-4ec3-a17c-97ece6881bc4",
	"name": "ASM 3",
	"values": [
		{
			"key": "url",
			"value": "http://13.228.39.1:5000",
			"type": "default",
			"enabled": true
		},
		{
			"key": "token_employer",
			"value": "",
			"type": "any",
			"enabled": true
		},
		{
			"key": "token_employee",
			"value": "",
			"type": "any",
			"enabled": true
		},
		{
			"key": "jobId",
			"value": "",
			"type": "any",
			"enabled": true
		}
	],
	"_postman_variable_scope": "environment",
	"_postman_exported_at": "2023-08-20T09:15:30.724Z",
	"_postman_exported_using": "Postman/10.17.2"
}